tagword/wordiscovery.py
tagword/tokenizer/__init__.py
tagword/tokenizer/basic.py
tagword/tokenizer/compat.py
tagword/tokenizer/crfpp.py
tagword/tokenizer/data_utils.py
tagword/tokenizer/hmm.py
tagword/tokenizer/makehmmmodel.py
tagword/tokenizer/makemaxmatchmodel.py
tagword/tokenizer/ops.py
tagword-0.1.dist-info/DESCRIPTION.rst
tagword-0.1.dist-info/METADATA
tagword-0.1.dist-info/RECORD
tagword-0.1.dist-info/WHEEL
tagword-0.1.dist-info/metadata.json
tagword-0.1.dist-info/top_level.txt
