Metadata-Version: 2.0
Name: tagword
Version: 0.1
Summary: A Chinese NLP toolkit
Home-page: https://github.com/ushiao/tagword
Author: Kun JIN
Author-email: jin.kun@flykun.com
License: MIT
Keywords: NLP,toolkit tokenizer
Platform: UNKNOWN
Classifier: Development Status :: 3 - Alpha
Classifier: Intended Audience :: Developers
Classifier: Topic :: Software Development :: Build Tools
Classifier: License :: OSI Approved :: MIT License
Classifier: Programming Language :: Python :: 3.5
Requires-Dist: six (==1.11.0)
Provides-Extra: dev
Requires-Dist: check-manifest; extra == 'dev'
Provides-Extra: test
Requires-Dist: coverage; extra == 'test'
